{"success":"true",
"msg":{"changeNumber":"DIR009","managerID":"solon","managerApprove":"Approve","itemRecords":[{"itemNumber":"D001","rowid":"908090","description":"AA项目任务书","rev":"1.0","managerReviewRecord":"同意","itemReviewRecords":[{"itemNumber":"D001","userid":"terry","specReview":"Generate New Spec","reason":"","documentNumber":"DXXX0009","ECNNumber":"ECN009"}]},{"itemNumber":"D002","rowid":"908092","description":"XX项目方案书","rev":"1.0","managerReviewRecord":"同意","itemReviewRecords":[{"itemNumber":"D002","userid":"terry","specReview":"不涉及","reason":"XX文档不需要转换","documentNumber":"","ECNNumber":"ECN009"}]}]}}